Metadata-Version: 2.1
Name: featherhelper
Version: 0.0.5
Summary: Feather Helper is a concise interface to cache numpy arrays and pandas dataframes.
Home-page: https://github.com/kiwi0fruit/featherhelper
Author: Peter Zagubisalo
Author-email: peter.zagubisalo@gmail.com
License: MIT
Platform: UNKNOWN
Classifier: Development Status :: 3 - Alpha
Classifier: Intended Audience :: Developers
Classifier: Topic :: Software Development :: Build Tools
Classifier: License :: OSI Approved :: MIT License
Classifier: Programming Language :: Python :: 3
Classifier: Programming Language :: Python :: 3.6
Requires-Python: >=3.6
